encrypt_decrypt_fields/__init__.py
encrypt_decrypt_fields/orm/__init__.py
encrypt_decrypt_fields/orm/alchemy_fields.py
encrypt_decrypt_fields/orm/django_fields.py
encrypt_decrypt_fields/services/__init__.py
encrypt_decrypt_fields/services/crypto.py
encrypt_decrypt_fields/tests/__init__.py
encrypt_decrypt_fields/tests/test_crypto.py
encrypt_decrypt_fields/tests/test_django_field.py
encrypt_decrypt_fields-1.3.6.dist-info/LICENSE
encrypt_decrypt_fields-1.3.6.dist-info/METADATA
encrypt_decrypt_fields-1.3.6.dist-info/WHEEL
encrypt_decrypt_fields-1.3.6.dist-info/RECORD
