Metadata-Version: 2.1
Name: encrypt-decrypt-fields
Version: 1.3.6
Summary: Encrypt and decrypt fields for a Django, SQLAlchemy ORM models or for direct use Crypto class
Home-page: https://github.com/alpden550/django-encrypt-decrypt
License: MIT
Keywords: django,django-orm,cryptography,development,orm,sqlachemy-orm
Author: Denis Novikov
Author-email: alpden550@gmail.com
Requires-Python: >=3.10,<4.0
Classifier: Development Status :: 5 - Production/Stable
Classifier: Environment :: Web Environment
Classifier: Framework :: Django
Classifier: Framework :: Django :: 3.2
Classifier: Intended Audience :: Developers
Classifier: License :: OSI Approved :: MIT License
Classifier: Operating System :: OS Independent
Classifier: Programming Language :: Python :: 3
Classifier: Programming Language :: Python :: 3.10
Classifier: Programming Language :: Python :: 3.11
Classifier: Programming Language :: Python :: 3.10
Classifier: Programming Language :: Python :: 3.11
Classifier: Programming Language :: Python :: Implementation
Classifier: Topic :: Software Development
Requires-Dist: Django
Requires-Dist: SQLAlchemy (>=1.4.19,<2.0.0)
Requires-Dist: cryptography (>=40.0.2,<42.0.0)
Project-URL: Repository, https://github.com/alpden550/django-encrypt-decrypt
